LICENSE
README.md
lyyinit.py
setup.py
lyyinit.egg-info/PKG-INFO
lyyinit.egg-info/SOURCES.txt
lyyinit.egg-info/dependency_links.txt
lyyinit.egg-info/top_level.txt