Metadata-Version: 2.1
Name: lyyinit
Version: 1.5
Summary: userfull application for  lyy
Author: lyy
Author-email: 
License: MIT
License-File: LICENSE
